LICENSE
MANIFEST.in
README.md
pyproject.toml
setup.py
kafka_broker_demoter/__init__.py
kafka_broker_demoter/cli.py
kafka_broker_demoter/configure_logging.py
kafka_broker_demoter/demoter.py
kafka_broker_demoter/exceptions.py
kafka_broker_demoter.egg-info/PKG-INFO
kafka_broker_demoter.egg-info/SOURCES.txt
kafka_broker_demoter.egg-info/dependency_links.txt
kafka_broker_demoter.egg-info/entry_points.txt
kafka_broker_demoter.egg-info/not-zip-safe
kafka_broker_demoter.egg-info/requires.txt
kafka_broker_demoter.egg-info/top_level.txt
requirements/requirements.txt